tbdebug/__init__.py
tbdebug/__main__.py
tbdump/__init__.py
tbdump/__main__.py
tbpeep/__init__.py
tbpeep/__main__.py
tibidi/__init__.py
tibidi/config_.py
tibidi/dumper.py
tibidi/loader.py
tibidi/pickler.py
tibidi-0.3.1.dist-info/LICENSE
tibidi-0.3.1.dist-info/WHEEL
tibidi-0.3.1.dist-info/METADATA
tibidi-0.3.1.dist-info/RECORD
