Metadata-Version: 2.1
Name: tibidi
Version: 0.3.1
Summary: Dump your traceback into a file.
Home-page: https://gergelyk.github.io/python-tibidi
License: MIT
Keywords: debug,dump,traceback
Author: Grzegorz Krasoń
Author-email: grzegorz.krason@gmail.com
Requires-Python: >=3.8,<4.0
Classifier: License :: OSI Approved :: MIT License
Classifier: Programming Language :: Python :: 3
Classifier: Programming Language :: Python :: 3.8
Requires-Dist: cloudpickle (>=1.6.0,<2.0.0)
Requires-Dist: peepshow (>=0.2.3,<0.3.0)
Project-URL: Documentation, https://gergelyk.github.io/python-tibidi
Project-URL: Repository, https://github.com/gergelyk/python-tibidi
